{"id":"017b-9c8508e85b","title":"Cosplay-抖娘利世-Atago-038-Takao-09-14","count":41,"cover":"https://telegra.ph/file/11b071771df86c5407b23.jpg","photos":[{"id":1,"url":"https://telegra.ph/file/11b071771df86c5407b23.jpg"},{"id":2,"url":"https://telegra.ph/file/25411605eed9abfefd1eb.jpg"},{"id":3,"url":"https://telegra.ph/file/5cbc306c65439262d7876.jpg"},{"id":4,"url":"https://telegra.ph/file/74c61444ceb10c0852715.jpg"},{"id":5,"url":"https://telegra.ph/file/67313be14232f9eacbc6b.jpg"},{"id":6,"url":"https://telegra.ph/file/b20374c9220b61641c003.jpg"},{"id":7,"url":"https://telegra.ph/file/88109a7d85b0dd3df2fa6.jpg"},{"id":8,"url":"https://telegra.ph/file/98c4ad1a8285661526bdc.jpg"},{"id":9,"url":"https://telegra.ph/file/672ef118987f0e6144368.jpg"},{"id":10,"url":"https://telegra.ph/file/969472804061e4cff92b4.jpg"},{"id":11,"url":"https://telegra.ph/file/2057e45f104ce04ef965c.jpg"},{"id":12,"url":"https://telegra.ph/file/9207c78a05045bfd63fbf.jpg"},{"id":13,"url":"https://telegra.ph/file/fbcc790578b88d9535ed3.jpg"},{"id":14,"url":"https://telegra.ph/file/0abb2879c43ffe76ab4cb.jpg"},{"id":15,"url":"https://telegra.ph/file/a5b1e797f3d67e640d917.jpg"},{"id":16,"url":"https://telegra.ph/file/85f2a7632055e415e3beb.jpg"},{"id":17,"url":"https://telegra.ph/file/59e54bdba1822075726a0.jpg"},{"id":18,"url":"https://telegra.ph/file/ccd2bfb7c6c4f50e989a2.jpg"},{"id":19,"url":"https://telegra.ph/file/ab50ccf11bde5850155c7.jpg"},{"id":20,"url":"https://telegra.ph/file/fbdd7dbf2858cb28e38f2.jpg"},{"id":21,"url":"https://telegra.ph/file/db358569dac21a335dab8.jpg"},{"id":22,"url":"https://telegra.ph/file/0a708b610ca575cbb8636.jpg"},{"id":23,"url":"https://telegra.ph/file/807530df55204750a6f45.jpg"},{"id":24,"url":"https://telegra.ph/file/aadc10453094549bbcc46.jpg"},{"id":25,"url":"https://telegra.ph/file/5521ed3c676ba6e7d01c2.jpg"},{"id":26,"url":"https://telegra.ph/file/3880ee597935edbaa9412.jpg"},{"id":27,"url":"https://telegra.ph/file/d1c81bcc14cd0a672750c.jpg"},{"id":28,"url":"https://telegra.ph/file/5af043924bc370e4d7633.jpg"},{"id":29,"url":"https://telegra.ph/file/6e6e7bc19dc2ed71b81e8.jpg"},{"id":30,"url":"https://telegra.ph/file/6d9be39de19122d210008.jpg"},{"id":31,"url":"https://telegra.ph/file/be18ee8af00f1e7cbd269.jpg"},{"id":32,"url":"https://telegra.ph/file/1c9dccd3e0065d6ee2f1a.jpg"},{"id":33,"url":"https://telegra.ph/file/1293cda532378150e3e7d.jpg"},{"id":34,"url":"https://telegra.ph/file/8bbac4989574337c8d64a.jpg"},{"id":35,"url":"https://telegra.ph/file/0d8e495e4e636124e65ab.jpg"},{"id":36,"url":"https://telegra.ph/file/a5abb47a15568dce43c5e.jpg"},{"id":37,"url":"https://telegra.ph/file/d1e1c0311d99cc766b519.jpg"},{"id":38,"url":"https://telegra.ph/file/36bc6b328c45bbd8c6f5e.jpg"},{"id":39,"url":"https://telegra.ph/file/2645483c77cb906899165.jpg"},{"id":40,"url":"https://telegra.ph/file/f76ddf039907d66c30483.jpg"},{"id":41,"url":"https://telegra.ph/file/d1313cfd6327e275d1c4c.jpg"}]}
