{"id":"01m7-1b226208a2","title":"042-千阳快起床---三花猫-12P-1217-MB-08-27","count":12,"cover":"https://telegra.ph/file/c581a39b86e9bd29ddfdf.jpg","photos":[{"id":1,"url":"https://telegra.ph/file/c581a39b86e9bd29ddfdf.jpg"},{"id":2,"url":"https://telegra.ph/file/cf38acd9f073971a43125.jpg"},{"id":3,"url":"https://telegra.ph/file/58e58a5962a8eec728771.jpg"},{"id":4,"url":"https://telegra.ph/file/11780a2d4ddf7a2dbb699.jpg"},{"id":5,"url":"https://telegra.ph/file/4558ad96f1f9733972fe0.jpg"},{"id":6,"url":"https://telegra.ph/file/440933aec74cbf75b8092.jpg"},{"id":7,"url":"https://telegra.ph/file/69260e21e933eb892b30c.jpg"},{"id":8,"url":"https://telegra.ph/file/519af4ea99c3682b9b619.jpg"},{"id":9,"url":"https://telegra.ph/file/3912d42e127baf188293b.jpg"},{"id":10,"url":"https://telegra.ph/file/e2e53477e2c28fa64eeeb.jpg"},{"id":11,"url":"https://telegra.ph/file/0d58b609b159d7cc96534.jpg"},{"id":12,"url":"https://telegra.ph/file/bc730b3fc8d18868d46d8.jpg"}]}
