{"id":"01r7-4ac09aad77","title":"099-XiuRen秀人网-20181126-NO1241-Angela小热巴-72P-1233-MB-08-24","count":72,"cover":"https://telegra.ph/file/b6dbd52c7f56e650e9e81.jpg","photos":[{"id":1,"url":"https://telegra.ph/file/b6dbd52c7f56e650e9e81.jpg"},{"id":2,"url":"https://telegra.ph/file/cc299ff14091e477d5d0a.jpg"},{"id":3,"url":"https://telegra.ph/file/00974764961cd7fd93b70.jpg"},{"id":4,"url":"https://telegra.ph/file/f59b33078e873140f21b4.jpg"},{"id":5,"url":"https://telegra.ph/file/5e371331afcf952101346.jpg"},{"id":6,"url":"https://telegra.ph/file/15a585d1c6814119bc36f.jpg"},{"id":7,"url":"https://telegra.ph/file/68474689e7be88021884f.jpg"},{"id":8,"url":"https://telegra.ph/file/ed200bbce8b291831e565.jpg"},{"id":9,"url":"https://telegra.ph/file/32aed5dd640f93dbcff0e.jpg"},{"id":10,"url":"https://telegra.ph/file/33d6e3cb1a57cd07364f8.jpg"},{"id":11,"url":"https://telegra.ph/file/35684881530b07f8818f8.jpg"},{"id":12,"url":"https://telegra.ph/file/fd73fd780d0057924f3ee.jpg"},{"id":13,"url":"https://telegra.ph/file/2a39dcf20a279ab1b6d1a.jpg"},{"id":14,"url":"https://telegra.ph/file/875e2f0741ba749f5591b.jpg"},{"id":15,"url":"https://telegra.ph/file/4a8c405474a9491de4b02.jpg"},{"id":16,"url":"https://telegra.ph/file/5aa1fcfb37b8b96c423b5.jpg"},{"id":17,"url":"https://telegra.ph/file/5d32a889cd2cb7f4ee838.jpg"},{"id":18,"url":"https://telegra.ph/file/7bacd5777a9299860054b.jpg"},{"id":19,"url":"https://telegra.ph/file/6ce64e79612de5be51af4.jpg"},{"id":20,"url":"https://telegra.ph/file/56bd9fdffd61a76642f7d.jpg"},{"id":21,"url":"https://telegra.ph/file/71c7d89a367bee04a3173.jpg"},{"id":22,"url":"https://telegra.ph/file/b320d280a3013c0d64087.jpg"},{"id":23,"url":"https://telegra.ph/file/83589712064e738e2403f.jpg"},{"id":24,"url":"https://telegra.ph/file/eef0f6fa53d73c066cce7.jpg"},{"id":25,"url":"https://telegra.ph/file/2def9aaa0443357de3b5c.jpg"},{"id":26,"url":"https://telegra.ph/file/90c4ee4e9f8ae10350bea.jpg"},{"id":27,"url":"https://telegra.ph/file/c44738e36aa028a1e35fe.jpg"},{"id":28,"url":"https://telegra.ph/file/c28cf780c8ef10336e682.jpg"},{"id":29,"url":"https://telegra.ph/file/a11fd9cdd37aecf3d49fb.jpg"},{"id":30,"url":"https://telegra.ph/file/0a2d10cf8e4922c6f244e.jpg"},{"id":31,"url":"https://telegra.ph/file/35650943fa10566ff0619.jpg"},{"id":32,"url":"https://telegra.ph/file/67e120edee1ef87daafd5.jpg"},{"id":33,"url":"https://telegra.ph/file/d02a1a3677166b8962df6.jpg"},{"id":34,"url":"https://telegra.ph/file/f814401aaceb36085aa62.jpg"},{"id":35,"url":"https://telegra.ph/file/f63c9fdd2cf1ad9cdf746.jpg"},{"id":36,"url":"https://telegra.ph/file/4b76419e37fa121b37d93.jpg"},{"id":37,"url":"https://telegra.ph/file/648410729b0a60938bea2.jpg"},{"id":38,"url":"https://telegra.ph/file/696ee3378d4bbe64f01d1.jpg"},{"id":39,"url":"https://telegra.ph/file/d8721f677f5d565dbce88.jpg"},{"id":40,"url":"https://telegra.ph/file/358e8c26cdd6ca2e7936c.jpg"},{"id":41,"url":"https://telegra.ph/file/d344dc2bc72d1ac2a0370.jpg"},{"id":42,"url":"https://telegra.ph/file/4be853cd68497fa410461.jpg"},{"id":43,"url":"https://telegra.ph/file/fdec3dc80e0dfdfd209f5.jpg"},{"id":44,"url":"https://telegra.ph/file/109b47770fd2a6cb076d4.jpg"},{"id":45,"url":"https://telegra.ph/file/c4b9c559545f3bed02d15.jpg"},{"id":46,"url":"https://telegra.ph/file/86c3081d7d41a154978c9.jpg"},{"id":47,"url":"https://telegra.ph/file/0ba3c88e641e6b1e9c710.jpg"},{"id":48,"url":"https://telegra.ph/file/554d87e036f3bce755ba5.jpg"},{"id":49,"url":"https://telegra.ph/file/cce4cd8c8fd3b66ac6994.jpg"},{"id":50,"url":"https://telegra.ph/file/ac2404a8a050ed0ae39c8.jpg"},{"id":51,"url":"https://telegra.ph/file/d00a388b22b979440f27d.jpg"},{"id":52,"url":"https://telegra.ph/file/fe578d89b4866e3ac725b.jpg"},{"id":53,"url":"https://telegra.ph/file/b00c5caa6196a5c492a00.jpg"},{"id":54,"url":"https://telegra.ph/file/63d24599e7232eb64be3c.jpg"},{"id":55,"url":"https://telegra.ph/file/4f0f597759f3aeeb4980c.jpg"},{"id":56,"url":"https://telegra.ph/file/e9743d0715b5858410a60.jpg"},{"id":57,"url":"https://telegra.ph/file/c2096ca978b35205e9106.jpg"},{"id":58,"url":"https://telegra.ph/file/c34e730747589295bad29.jpg"},{"id":59,"url":"https://telegra.ph/file/86fef8f5615d7599544c3.jpg"},{"id":60,"url":"https://telegra.ph/file/38daa1c553d0f09fbc742.jpg"},{"id":61,"url":"https://telegra.ph/file/ea78d252189ec7850367d.jpg"},{"id":62,"url":"https://telegra.ph/file/23aa598fff610420342bd.jpg"},{"id":63,"url":"https://telegra.ph/file/d6f5daf420d5fe2b67987.jpg"},{"id":64,"url":"https://telegra.ph/file/0f850e28ea79c31875bae.jpg"},{"id":65,"url":"https://telegra.ph/file/306cb9a04836352ddeb45.jpg"},{"id":66,"url":"https://telegra.ph/file/ca49afa49dca872540788.jpg"},{"id":67,"url":"https://telegra.ph/file/9277f84404fa0bd77ee1f.jpg"},{"id":68,"url":"https://telegra.ph/file/3eb1e22580c503fdd2e4a.jpg"},{"id":69,"url":"https://telegra.ph/file/d3316a3f67e26cb49e7ed.jpg"},{"id":70,"url":"https://telegra.ph/file/13777ae3c7623fa4e62c2.jpg"},{"id":71,"url":"https://telegra.ph/file/791c4de1907529f79e702.jpg"},{"id":72,"url":"https://telegra.ph/file/bf98989ab3169a429d24d.jpg"}]}
