{"id":"03nw-1101faed2d","title":"149-05-15","count":15,"cover":"https://telegra.ph/file/84f435aae97ac0ff18583.jpg","photos":[{"id":1,"url":"https://telegra.ph/file/84f435aae97ac0ff18583.jpg"},{"id":2,"url":"https://telegra.ph/file/d32a14c23adc285ea0c3b.jpg"},{"id":3,"url":"https://telegra.ph/file/f80b794ec7b36a14e9a09.jpg"},{"id":4,"url":"https://telegra.ph/file/3b7876097fcbae563de60.jpg"},{"id":5,"url":"https://telegra.ph/file/efffeeee379afa64ae6be.jpg"},{"id":6,"url":"https://telegra.ph/file/2c44dcd3cf3aef9421012.jpg"},{"id":7,"url":"https://telegra.ph/file/16125974fe5875e49a033.jpg"},{"id":8,"url":"https://telegra.ph/file/f535337be91297ce8e77a.jpg"},{"id":9,"url":"https://telegra.ph/file/7e644f027acb31de095ab.jpg"},{"id":10,"url":"https://telegra.ph/file/d4ac9608de788ce2c8e76.jpg"},{"id":11,"url":"https://telegra.ph/file/2e568b7e68d65a7c2c4cc.jpg"},{"id":12,"url":"https://telegra.ph/file/7d5d1952c440c81030242.jpg"},{"id":13,"url":"https://telegra.ph/file/a74c4f342006d3bac05aa.jpg"},{"id":14,"url":"https://telegra.ph/file/404c1de550e0cb4eb7a69.jpg"},{"id":15,"url":"https://telegra.ph/file/b210287397ea9b655e222.jpg"}]}
