{"id":"04rt-0106a586ba","title":"柚木-第02季-母狗tiao教-14P-03-10","count":14,"cover":"https://telegra.ph/file/e7e970e13c73c758ca846.jpg","photos":[{"id":1,"url":"https://telegra.ph/file/e7e970e13c73c758ca846.jpg"},{"id":2,"url":"https://telegra.ph/file/8fc9ec5ed635ca35a328d.jpg"},{"id":3,"url":"https://telegra.ph/file/4bfd08f2aa17e96b5f99c.jpg"},{"id":4,"url":"https://telegra.ph/file/b9bc6f051b0ff91b53383.jpg"},{"id":5,"url":"https://telegra.ph/file/939739ace5da10565ea7c.jpg"},{"id":6,"url":"https://telegra.ph/file/b0ec855473169168e3a98.jpg"},{"id":7,"url":"https://telegra.ph/file/9163824a839d13e1a4ab7.jpg"},{"id":8,"url":"https://telegra.ph/file/016630d1d1ed379bc904e.jpg"},{"id":9,"url":"https://telegra.ph/file/14bc9a6552b01e761afba.jpg"},{"id":10,"url":"https://telegra.ph/file/66b7307edf4c89276faa5.jpg"},{"id":11,"url":"https://telegra.ph/file/39721edc3e282f6ed2655.jpg"},{"id":12,"url":"https://telegra.ph/file/001c898bbb95014b047ba.jpg"},{"id":13,"url":"https://telegra.ph/file/f4a0cc2ec97ea26f67d49.jpg"},{"id":14,"url":"https://telegra.ph/file/6f8e357a730bdae6980a8.jpg"}]}
