{"id":"06ax-ea51746488","title":"渡边爻爻子---黑色蕾丝-31P-518MB-20240626h-06-26","count":31,"cover":"https://telegra.ph/file/21b4df3cac5ff870c4c99.jpg","photos":[{"id":1,"url":"https://telegra.ph/file/21b4df3cac5ff870c4c99.jpg"},{"id":2,"url":"https://telegra.ph/file/b65878cde2a262a506da7.jpg"},{"id":3,"url":"https://telegra.ph/file/9172c8c7397b0f6ce3691.jpg"},{"id":4,"url":"https://telegra.ph/file/fa20e57c5331b2cd21763.jpg"},{"id":5,"url":"https://telegra.ph/file/d9cb5041a714f1873beb6.jpg"},{"id":6,"url":"https://telegra.ph/file/d45a71922abb14e48599b.jpg"},{"id":7,"url":"https://telegra.ph/file/53cf2f0261218c5ed3d03.jpg"},{"id":8,"url":"https://telegra.ph/file/f30e402e1962f9dab2cec.jpg"},{"id":9,"url":"https://telegra.ph/file/c7538eed70d45574079bb.jpg"},{"id":10,"url":"https://telegra.ph/file/b899830f477f779e3a5a0.jpg"},{"id":11,"url":"https://telegra.ph/file/8240d2e57be171365592c.jpg"},{"id":12,"url":"https://telegra.ph/file/a26df1cfbc7ed4c7c8a07.jpg"},{"id":13,"url":"https://telegra.ph/file/cac0ca9346e2e01ea5858.jpg"},{"id":14,"url":"https://telegra.ph/file/8100b50a6fab00a5f382e.jpg"},{"id":15,"url":"https://telegra.ph/file/3c3fe64a1f72eefb82260.jpg"},{"id":16,"url":"https://telegra.ph/file/3c6af36797a422ab1dcfd.jpg"},{"id":17,"url":"https://telegra.ph/file/85eb0383ad43a1afb6924.jpg"},{"id":18,"url":"https://telegra.ph/file/0619521b84dcb9643b3de.jpg"},{"id":19,"url":"https://telegra.ph/file/35cb140affafefc65d60c.jpg"},{"id":20,"url":"https://telegra.ph/file/c8763a15247531d264e2f.jpg"},{"id":21,"url":"https://telegra.ph/file/152c05661b965d088bc5b.jpg"},{"id":22,"url":"https://telegra.ph/file/a242260d4102766301766.jpg"},{"id":23,"url":"https://telegra.ph/file/bafcbca418b682de911bf.jpg"},{"id":24,"url":"https://telegra.ph/file/bf5c7e3c08a56fdcd3df3.jpg"},{"id":25,"url":"https://telegra.ph/file/140368d7a592f83e2ffd2.jpg"},{"id":26,"url":"https://telegra.ph/file/5915b0952606d89b6a619.jpg"},{"id":27,"url":"https://telegra.ph/file/65a56e1fbb0211b5e2942.jpg"},{"id":28,"url":"https://telegra.ph/file/a0f0a7e5d4a5afa18cab5.jpg"},{"id":29,"url":"https://telegra.ph/file/0336d015812a5d2fc0bb8.jpg"},{"id":30,"url":"https://telegra.ph/file/4f085856901e22cdbe899.jpg"},{"id":31,"url":"https://telegra.ph/file/af153e8dffef72f7a932e.jpg"}]}
