{"id":"07vh-00ee251bfb","title":"九柒喵-碧蓝档案-妃咲-07-15-2","count":28,"cover":"https://telegra.ph/file/a62b02caefe495bf649f3.jpg","photos":[{"id":1,"url":"https://telegra.ph/file/a62b02caefe495bf649f3.jpg"},{"id":2,"url":"https://telegra.ph/file/41305d3fd94efe5bf6c7f.jpg"},{"id":3,"url":"https://telegra.ph/file/a34b8e203795595b26240.jpg"},{"id":4,"url":"https://telegra.ph/file/3af7f968b68792c4dd40f.jpg"},{"id":5,"url":"https://telegra.ph/file/e3667f3d489deb5c349fb.jpg"},{"id":6,"url":"https://telegra.ph/file/434ac09b2836e01960d61.jpg"},{"id":7,"url":"https://telegra.ph/file/ed1f15ef7bd8f13d27cb3.jpg"},{"id":8,"url":"https://telegra.ph/file/6ed8bb8efe5d9e5cd83ee.jpg"},{"id":9,"url":"https://telegra.ph/file/18b79cadefb78b1191556.jpg"},{"id":10,"url":"https://telegra.ph/file/4dd4ddcb39e964ae2bf7d.jpg"},{"id":11,"url":"https://telegra.ph/file/30c425d551d18ddb556da.jpg"},{"id":12,"url":"https://telegra.ph/file/020a575355686b309aab0.jpg"},{"id":13,"url":"https://telegra.ph/file/f1a7e79fd291ffe9c98f4.jpg"},{"id":14,"url":"https://telegra.ph/file/cc49b77ff95e8e1e3e940.jpg"},{"id":15,"url":"https://telegra.ph/file/91ccf4dd7c4ecac84958d.jpg"},{"id":16,"url":"https://telegra.ph/file/158f8d3bdfbf3bdf1ade5.jpg"},{"id":17,"url":"https://telegra.ph/file/9b803b7299d9cf50e2114.jpg"},{"id":18,"url":"https://telegra.ph/file/f2d3fdfc5c563807d6143.jpg"},{"id":19,"url":"https://telegra.ph/file/b063029b0d8acce5f719b.jpg"},{"id":20,"url":"https://telegra.ph/file/9fb8835eb9bd4877c97c7.jpg"},{"id":21,"url":"https://telegra.ph/file/a9e22691b36adeada2e06.jpg"},{"id":22,"url":"https://telegra.ph/file/ddff8e7a2ef9c9172a851.jpg"},{"id":23,"url":"https://telegra.ph/file/bc08361c6be675eb247b0.jpg"},{"id":24,"url":"https://telegra.ph/file/924ad3587bb062c3445a7.jpg"},{"id":25,"url":"https://telegra.ph/file/4644c7de7a4b971532881.jpg"},{"id":26,"url":"https://telegra.ph/file/6c8b696620c702db5a407.jpg"},{"id":27,"url":"https://telegra.ph/file/3ab045821db38202baa8c.jpg"},{"id":28,"url":"https://telegra.ph/file/ab05eaf75ddfa6188ea6d.jpg"}]}
