{"id":"080c-ac9e9c1c63","title":"就是阿朱啊--NO046-兔子22P-909M-07-09","count":22,"cover":"https://telegra.ph/file/72e8a35b29c0028511895.jpg","photos":[{"id":1,"url":"https://telegra.ph/file/72e8a35b29c0028511895.jpg"},{"id":2,"url":"https://telegra.ph/file/a01230eb10b707087414b.jpg"},{"id":3,"url":"https://telegra.ph/file/35bda8d68452236483d68.jpg"},{"id":4,"url":"https://telegra.ph/file/6189ab30afe5a864b4be7.jpg"},{"id":5,"url":"https://telegra.ph/file/5661e1cdb6f095e441f5b.jpg"},{"id":6,"url":"https://telegra.ph/file/371615ab86637ae8f4474.jpg"},{"id":7,"url":"https://telegra.ph/file/a982023f9a91f3f478c2e.jpg"},{"id":8,"url":"https://telegra.ph/file/a009595cbbdf4e98fbdcb.jpg"},{"id":9,"url":"https://telegra.ph/file/d22ff46d3efb741f01d6e.jpg"},{"id":10,"url":"https://telegra.ph/file/bf88df658256a14644657.jpg"},{"id":11,"url":"https://telegra.ph/file/eb0ab384b0a1b281539d2.jpg"},{"id":12,"url":"https://telegra.ph/file/8bff45e3b8ef19e0612a8.jpg"},{"id":13,"url":"https://telegra.ph/file/62bc8645569ad9400e400.jpg"},{"id":14,"url":"https://telegra.ph/file/63b76157d6b40b6171dcf.jpg"},{"id":15,"url":"https://telegra.ph/file/6a34fcbc53c94db0f820c.jpg"},{"id":16,"url":"https://telegra.ph/file/a952d6e80828675803bd3.jpg"},{"id":17,"url":"https://telegra.ph/file/e0926430cc75458e62c08.jpg"},{"id":18,"url":"https://telegra.ph/file/8570017547302d9b96e67.jpg"},{"id":19,"url":"https://telegra.ph/file/c47b2741f7d0f9130b40c.jpg"},{"id":20,"url":"https://telegra.ph/file/e8624c100fc96a3fe3a32.jpg"},{"id":21,"url":"https://telegra.ph/file/4508a27a7b111536e22b3.jpg"},{"id":22,"url":"https://telegra.ph/file/2621bb259ed9ba29c1647.jpg"}]}
