{"id":"0865-014537a401","title":"009-霜月shimo-玉藻前-15P-29387-MB-07-04","count":15,"cover":"https://telegra.ph/file/e5100b34607025c98b1d8.jpg","photos":[{"id":1,"url":"https://telegra.ph/file/e5100b34607025c98b1d8.jpg"},{"id":2,"url":"https://telegra.ph/file/7290851a7881871d794e3.jpg"},{"id":3,"url":"https://telegra.ph/file/cde3cb49d0940f447aa05.jpg"},{"id":4,"url":"https://telegra.ph/file/f8d1940b1ae35b370ab1a.jpg"},{"id":5,"url":"https://telegra.ph/file/22397146fbd8fba0aad37.jpg"},{"id":6,"url":"https://telegra.ph/file/ac64b4b0cb3c3e8116d5c.jpg"},{"id":7,"url":"https://telegra.ph/file/b2a111db3477be7633459.jpg"},{"id":8,"url":"https://telegra.ph/file/c59b0f9ee4a4ea9a24338.jpg"},{"id":9,"url":"https://telegra.ph/file/45f109daa39f00ef601a2.jpg"},{"id":10,"url":"https://telegra.ph/file/02737c032356df73437ab.jpg"},{"id":11,"url":"https://telegra.ph/file/0cd27447679b299db3823.jpg"},{"id":12,"url":"https://telegra.ph/file/3474945de08d97921eb1c.jpg"},{"id":13,"url":"https://telegra.ph/file/d7332c361840ff245f59b.jpg"},{"id":14,"url":"https://telegra.ph/file/9144615d3396ea0e0926f.jpg"},{"id":15,"url":"https://telegra.ph/file/43cd0d32072f0da092b82.jpg"}]}
