{"id":"08r6-00bc0ec244","title":"桃良阿宅---地铁-06-12","count":41,"cover":"https://telegra.ph/file/ec52faa3cffd54c40b92e.jpg","photos":[{"id":1,"url":"https://telegra.ph/file/ec52faa3cffd54c40b92e.jpg"},{"id":2,"url":"https://telegra.ph/file/af4898f682f43af3c5682.jpg"},{"id":3,"url":"https://telegra.ph/file/a1c4fec1005e3c6bfe311.jpg"},{"id":4,"url":"https://telegra.ph/file/313a1a6381e082950cb54.jpg"},{"id":5,"url":"https://telegra.ph/file/92dc8151066d219b7d9e9.jpg"},{"id":6,"url":"https://telegra.ph/file/55a5cf3f33f8aafe99fb5.jpg"},{"id":7,"url":"https://telegra.ph/file/ee7908092a29faae2427b.jpg"},{"id":8,"url":"https://telegra.ph/file/6a06163b1ec6d10a4b4b4.jpg"},{"id":9,"url":"https://telegra.ph/file/f25c9bbbe54222b3eefeb.jpg"},{"id":10,"url":"https://telegra.ph/file/ea9f07d7e90191739602c.jpg"},{"id":11,"url":"https://telegra.ph/file/9825fc82befe20a7fc39f.jpg"},{"id":12,"url":"https://telegra.ph/file/cee9d0302cea201265ebf.jpg"},{"id":13,"url":"https://telegra.ph/file/99109b692c03ecfbbc9db.jpg"},{"id":14,"url":"https://telegra.ph/file/d7eb0fd12e4d633daa7ed.jpg"},{"id":15,"url":"https://telegra.ph/file/769cb8810e3bc3a983e4c.jpg"},{"id":16,"url":"https://telegra.ph/file/825eecea94453b034d170.jpg"},{"id":17,"url":"https://telegra.ph/file/8dfd3d8c2cd88be29b80c.jpg"},{"id":18,"url":"https://telegra.ph/file/8f4ad9ef2a2921a3cfc7d.jpg"},{"id":19,"url":"https://telegra.ph/file/acfe5afd37268ca0ef5a4.jpg"},{"id":20,"url":"https://telegra.ph/file/f363ab49af270385480fb.jpg"},{"id":21,"url":"https://telegra.ph/file/0b5a4ac7741ec15d9e85d.jpg"},{"id":22,"url":"https://telegra.ph/file/ca06b2225eebbcdfa9884.jpg"},{"id":23,"url":"https://telegra.ph/file/1fd937eb3330d956171bf.jpg"},{"id":24,"url":"https://telegra.ph/file/572ad6c614d8840331d7d.jpg"},{"id":25,"url":"https://telegra.ph/file/935188ac9fc7cab79b9e5.jpg"},{"id":26,"url":"https://telegra.ph/file/99087bff6da9652ca9cc5.jpg"},{"id":27,"url":"https://telegra.ph/file/191c7397b74b0af740280.jpg"},{"id":28,"url":"https://telegra.ph/file/74553f8bdcd8a952aed4b.jpg"},{"id":29,"url":"https://telegra.ph/file/263e0012ad2f3c16edfbb.jpg"},{"id":30,"url":"https://telegra.ph/file/a1b68688d316ce6ade2b2.jpg"},{"id":31,"url":"https://telegra.ph/file/17a93884d8c5995c4a812.jpg"},{"id":32,"url":"https://telegra.ph/file/8e3b09548e2f31417302c.jpg"},{"id":33,"url":"https://telegra.ph/file/c4684d0f50602c774dac4.jpg"},{"id":34,"url":"https://telegra.ph/file/4885287964784d108eb14.jpg"},{"id":35,"url":"https://telegra.ph/file/fe2c9bae1baffa50c9d09.jpg"},{"id":36,"url":"https://telegra.ph/file/1f24e1252c1d1c39de1ed.jpg"},{"id":37,"url":"https://telegra.ph/file/bd0fbba527aa19e7be43b.jpg"},{"id":38,"url":"https://telegra.ph/file/4c5f5b47b8cf0ab5b88df.jpg"},{"id":39,"url":"https://telegra.ph/file/a2f42eb5d1cb7cb196130.jpg"},{"id":40,"url":"https://telegra.ph/file/cf2c86dc185147710fa84.jpg"},{"id":41,"url":"https://telegra.ph/file/95197907befec3aa43158.jpg"}]}
