{"id":"08ze-f1eedb2b98","title":"000-29-Azami---超级索尼子-10P-472-MB-05-31","count":10,"cover":"https://telegra.ph/file/88f0995bc7b4bc611aa72.jpg","photos":[{"id":1,"url":"https://telegra.ph/file/88f0995bc7b4bc611aa72.jpg"},{"id":2,"url":"https://telegra.ph/file/dd5c0346f7dac5aae4e5b.jpg"},{"id":3,"url":"https://telegra.ph/file/3d98790ea06add7f605a4.jpg"},{"id":4,"url":"https://telegra.ph/file/83aeee88e16d1216ff338.jpg"},{"id":5,"url":"https://telegra.ph/file/b8145825e5fd3a32e44fe.jpg"},{"id":6,"url":"https://telegra.ph/file/f6deb2240e5554e8f9f6a.jpg"},{"id":7,"url":"https://telegra.ph/file/4baada4508f48014d977d.jpg"},{"id":8,"url":"https://telegra.ph/file/940137d3dfb03a9a06920.jpg"},{"id":9,"url":"https://telegra.ph/file/011cc65df9356c851d932.jpg"},{"id":10,"url":"https://telegra.ph/file/0c223d706bb450fbd05c8.jpg"}]}
