{"id":"0aes-07bcf45ee5","title":"微密圈-黎允熙baby私房图集4100P-03-06","count":77,"cover":"https://telegra.ph/file/66c512b6a374ec1fab076.jpg","photos":[{"id":1,"url":"https://telegra.ph/file/66c512b6a374ec1fab076.jpg"},{"id":2,"url":"https://telegra.ph/file/8a9808352c9e16f500ab0.jpg"},{"id":3,"url":"https://telegra.ph/file/6191fc4ecc5836c8268a2.jpg"},{"id":4,"url":"https://telegra.ph/file/02b56b690e0b6a468df95.jpg"},{"id":5,"url":"https://telegra.ph/file/4cbbba098a4d4fb31dd41.jpg"},{"id":6,"url":"https://telegra.ph/file/52351c659a034fb606b51.jpg"},{"id":7,"url":"https://telegra.ph/file/6a61b51fad513717a0eab.jpg"},{"id":8,"url":"https://telegra.ph/file/cebb28d564e5e8445aa8b.jpg"},{"id":9,"url":"https://telegra.ph/file/9318403c63f79d846d900.jpg"},{"id":10,"url":"https://telegra.ph/file/11aeffe2623e42e7263a4.jpg"},{"id":11,"url":"https://telegra.ph/file/54575404e6fd73d522916.jpg"},{"id":12,"url":"https://telegra.ph/file/2b56203db2cbc0cdce236.jpg"},{"id":13,"url":"https://telegra.ph/file/631e8ad17a7690167367a.jpg"},{"id":14,"url":"https://telegra.ph/file/a7dee22756ed1a3b09450.jpg"},{"id":15,"url":"https://telegra.ph/file/529881fa3155dd1f6a41e.jpg"},{"id":16,"url":"https://telegra.ph/file/65732cca6747ece222eab.jpg"},{"id":17,"url":"https://telegra.ph/file/6005dc774b835bc092540.jpg"},{"id":18,"url":"https://telegra.ph/file/77b0f6a0e2aa0a56e94a7.jpg"},{"id":19,"url":"https://telegra.ph/file/5aa80adb638a56f717c55.jpg"},{"id":20,"url":"https://telegra.ph/file/5819e9dc1a5f349cab4e9.jpg"},{"id":21,"url":"https://telegra.ph/file/45f5822477f26b797ea18.jpg"},{"id":22,"url":"https://telegra.ph/file/b51ff4269304c58ae8d4a.jpg"},{"id":23,"url":"https://telegra.ph/file/777422a234c20f47dfc93.jpg"},{"id":24,"url":"https://telegra.ph/file/2856996bab10ac9fb4f96.jpg"},{"id":25,"url":"https://telegra.ph/file/d91895a0858dd6120d417.jpg"},{"id":26,"url":"https://telegra.ph/file/41811436f938e6546bcca.jpg"},{"id":27,"url":"https://telegra.ph/file/93dd891c9eb2e02686a36.jpg"},{"id":28,"url":"https://telegra.ph/file/181f32b3e6e3f5d3d915a.jpg"},{"id":29,"url":"https://telegra.ph/file/7a62e2b14ce7746ed8c01.jpg"},{"id":30,"url":"https://telegra.ph/file/cee9a0ca462de198ec0c8.jpg"},{"id":31,"url":"https://telegra.ph/file/2d8279855b915546b41f0.jpg"},{"id":32,"url":"https://telegra.ph/file/794ddadc75eab0d31a950.jpg"},{"id":33,"url":"https://telegra.ph/file/eca62e9974af568500740.jpg"},{"id":34,"url":"https://telegra.ph/file/b9b07ccd7b2b5e46ec53b.jpg"},{"id":35,"url":"https://telegra.ph/file/b7b572fa406fe4064acef.jpg"},{"id":36,"url":"https://telegra.ph/file/2988f20a1411bb876070b.jpg"},{"id":37,"url":"https://telegra.ph/file/d775e0a82cd28c385c839.jpg"},{"id":38,"url":"https://telegra.ph/file/2dea35c217b0dcbec4330.jpg"},{"id":39,"url":"https://telegra.ph/file/c2d5e9484045c38a616d7.jpg"},{"id":40,"url":"https://telegra.ph/file/0816dc671e7835b80fa20.jpg"},{"id":41,"url":"https://telegra.ph/file/0baef6e6cbff8574ffcaf.jpg"},{"id":42,"url":"https://telegra.ph/file/768288f74910edd7fd824.jpg"},{"id":43,"url":"https://telegra.ph/file/b22f1eceddc9fdd30c2f9.jpg"},{"id":44,"url":"https://telegra.ph/file/7282f100264a9058faa41.jpg"},{"id":45,"url":"https://telegra.ph/file/1c9525235586f0ff01200.jpg"},{"id":46,"url":"https://telegra.ph/file/9977ce00bac71f4899c19.jpg"},{"id":47,"url":"https://telegra.ph/file/a5a9634e655de2a76c5b9.jpg"},{"id":48,"url":"https://telegra.ph/file/5d1dbde433c43d8ecca60.jpg"},{"id":49,"url":"https://telegra.ph/file/ee7235697652bcd427ed8.jpg"},{"id":50,"url":"https://telegra.ph/file/e4bb42edb758f3e0e5118.jpg"},{"id":51,"url":"https://telegra.ph/file/3c074b68b8c0c0c7973a0.jpg"},{"id":52,"url":"https://telegra.ph/file/1063afbcd9cc01f0dd87b.jpg"},{"id":53,"url":"https://telegra.ph/file/235a89cf57189f205dc13.jpg"},{"id":54,"url":"https://telegra.ph/file/f2009b4823dec7665df34.jpg"},{"id":55,"url":"https://telegra.ph/file/7629ea82964daa253cda3.jpg"},{"id":56,"url":"https://telegra.ph/file/5e987db93cec22145f9cc.jpg"},{"id":57,"url":"https://telegra.ph/file/574fd843075c0999728cd.jpg"},{"id":58,"url":"https://telegra.ph/file/a7a8f3111149fb5c1c24e.jpg"},{"id":59,"url":"https://telegra.ph/file/2085befbd676116e6b9f5.jpg"},{"id":60,"url":"https://telegra.ph/file/c3ea4dc11996c341c5565.jpg"},{"id":61,"url":"https://telegra.ph/file/95cca09a37e7229f361bc.jpg"},{"id":62,"url":"https://telegra.ph/file/cb18ddc713fcd48f4e4ae.jpg"},{"id":63,"url":"https://telegra.ph/file/3fdb0a0b50593153a5d12.jpg"},{"id":64,"url":"https://telegra.ph/file/3844c90434e934002dd16.jpg"},{"id":65,"url":"https://telegra.ph/file/765173759e3895fae1377.jpg"},{"id":66,"url":"https://telegra.ph/file/e4b31d9c50ba7516aa111.jpg"},{"id":67,"url":"https://telegra.ph/file/648308046411d1cd42467.jpg"},{"id":68,"url":"https://telegra.ph/file/bec9e537e0d18300e35d7.jpg"},{"id":69,"url":"https://telegra.ph/file/5c9e9eca1a9be48822255.jpg"},{"id":70,"url":"https://telegra.ph/file/25c93be0a41040c6f5a5d.jpg"},{"id":71,"url":"https://telegra.ph/file/49963a41ca88f306d1b3d.jpg"},{"id":72,"url":"https://telegra.ph/file/5eb29163d688ae841fae5.jpg"},{"id":73,"url":"https://telegra.ph/file/34520c25e8e3a59351bf1.jpg"},{"id":74,"url":"https://telegra.ph/file/a98a7dd8b9aad94fe27b7.jpg"},{"id":75,"url":"https://telegra.ph/file/a32b7ff400188b5c2cc14.jpg"},{"id":76,"url":"https://telegra.ph/file/71331638da868b3b396f9.jpg"},{"id":77,"url":"https://telegra.ph/file/9c622a397c35dbeeffb74.jpg"}]}
