{"id":"0aq9-b0221df04e","title":"布丁大法-黑丝吊带情趣-09-13","count":124,"cover":"https://telegra.ph/file/27f3200fbc3e9e9628212.jpg","photos":[{"id":1,"url":"https://telegra.ph/file/27f3200fbc3e9e9628212.jpg"},{"id":2,"url":"https://telegra.ph/file/7422e895ee37275252b83.jpg"},{"id":3,"url":"https://telegra.ph/file/6c66952ff3aeff0768618.jpg"},{"id":4,"url":"https://telegra.ph/file/fd7b04afe33b6aa413cac.jpg"},{"id":5,"url":"https://telegra.ph/file/bf48a5d6001f9b413cea3.jpg"},{"id":6,"url":"https://telegra.ph/file/358711d85f484150257a5.jpg"},{"id":7,"url":"https://telegra.ph/file/f605a9cd6b4747be0ed50.jpg"},{"id":8,"url":"https://telegra.ph/file/b29a0d96444d8cc5e91ce.jpg"},{"id":9,"url":"https://telegra.ph/file/5ed6965df477fe62e241c.jpg"},{"id":10,"url":"https://telegra.ph/file/62b5d3c75906e54935748.jpg"},{"id":11,"url":"https://telegra.ph/file/f26f7a19d76b79ff84a3f.jpg"},{"id":12,"url":"https://telegra.ph/file/1be67311dd99a23d0e2fb.jpg"},{"id":13,"url":"https://telegra.ph/file/a0f40acb5df8616ba0143.jpg"},{"id":14,"url":"https://telegra.ph/file/7f8cf17d3bd3f4a341396.jpg"},{"id":15,"url":"https://telegra.ph/file/6b32f1ef6afb39511a6da.jpg"},{"id":16,"url":"https://telegra.ph/file/82339214246c79ce06753.jpg"},{"id":17,"url":"https://telegra.ph/file/f82fc2d1d7fc9f9b23673.jpg"},{"id":18,"url":"https://telegra.ph/file/729eea960574ae2aa74e2.jpg"},{"id":19,"url":"https://telegra.ph/file/2bb6e8bfe936b17ca2cca.jpg"},{"id":20,"url":"https://telegra.ph/file/1f1bd9888432e5edb11db.jpg"},{"id":21,"url":"https://telegra.ph/file/8c150e53ed95350ea748d.jpg"},{"id":22,"url":"https://telegra.ph/file/6fffa75adc4979e05745b.jpg"},{"id":23,"url":"https://telegra.ph/file/d2f3009e3e2a16b9c0966.jpg"},{"id":24,"url":"https://telegra.ph/file/4cbf48a9f748a520fa400.jpg"},{"id":25,"url":"https://telegra.ph/file/a72c206115d3d3cc8eeb9.jpg"},{"id":26,"url":"https://telegra.ph/file/47b3e952668af22f1de28.jpg"},{"id":27,"url":"https://telegra.ph/file/51cf3c15adc6076b2d863.jpg"},{"id":28,"url":"https://telegra.ph/file/6f514ff0540b852d3f6b0.jpg"},{"id":29,"url":"https://telegra.ph/file/529d303e104001a4600a7.jpg"},{"id":30,"url":"https://telegra.ph/file/127a4f60344a51e7fcd2e.jpg"},{"id":31,"url":"https://telegra.ph/file/321a10822e1903773b75f.jpg"},{"id":32,"url":"https://telegra.ph/file/7707289aa216df929337d.jpg"},{"id":33,"url":"https://telegra.ph/file/8a8e2f75ff8c30fe953ad.jpg"},{"id":34,"url":"https://telegra.ph/file/c4bb9080e2e4cb55d57ec.jpg"},{"id":35,"url":"https://telegra.ph/file/2f465aa9ae0ade2376d12.jpg"},{"id":36,"url":"https://telegra.ph/file/942007c9f3a4a2b4db8f8.jpg"},{"id":37,"url":"https://telegra.ph/file/b2afedc96d81da1827076.jpg"},{"id":38,"url":"https://telegra.ph/file/73244a0902d2abc10e6f0.jpg"},{"id":39,"url":"https://telegra.ph/file/05d27fc1a1c165077d1b5.jpg"},{"id":40,"url":"https://telegra.ph/file/c339ce1ee132c6a1cb29c.jpg"},{"id":41,"url":"https://telegra.ph/file/f9b0a412639947014ad1d.jpg"},{"id":42,"url":"https://telegra.ph/file/7d9454d1e801dd72846dd.jpg"},{"id":43,"url":"https://telegra.ph/file/291b455f65ac3ea9ef2e0.jpg"},{"id":44,"url":"https://telegra.ph/file/af39b504cb25a815b92af.jpg"},{"id":45,"url":"https://telegra.ph/file/7f4258f525d370df51a04.jpg"},{"id":46,"url":"https://telegra.ph/file/0ff2a52344f607fe54f32.jpg"},{"id":47,"url":"https://telegra.ph/file/ccbe0065268e150dc3532.jpg"},{"id":48,"url":"https://telegra.ph/file/d0c0fc7eaa553524cc14d.jpg"},{"id":49,"url":"https://telegra.ph/file/61a7de6fd0acde07c7e73.jpg"},{"id":50,"url":"https://telegra.ph/file/c2a366664359c4c0d19ac.jpg"},{"id":51,"url":"https://telegra.ph/file/fb0de93c9fb564a9681e9.jpg"},{"id":52,"url":"https://telegra.ph/file/bd78bf18874555c6043d7.jpg"},{"id":53,"url":"https://telegra.ph/file/e3ca317b14aaf104a34bc.jpg"},{"id":54,"url":"https://telegra.ph/file/b3592631cfbad170cf58c.jpg"},{"id":55,"url":"https://telegra.ph/file/e582ca427c033606a547d.jpg"},{"id":56,"url":"https://telegra.ph/file/3176e94eb66a30aa3cf74.jpg"},{"id":57,"url":"https://telegra.ph/file/33fd70ef22657ea991812.jpg"},{"id":58,"url":"https://telegra.ph/file/1b847a2208b2a827cec5e.jpg"},{"id":59,"url":"https://telegra.ph/file/80dbfe5af0dd2a8971de6.jpg"},{"id":60,"url":"https://telegra.ph/file/8478c21ca915a2f3ada24.jpg"},{"id":61,"url":"https://telegra.ph/file/92a273b20a1107d198cb3.jpg"},{"id":62,"url":"https://telegra.ph/file/8c5671af34bada36bdc42.jpg"},{"id":63,"url":"https://telegra.ph/file/d98d3511b0f8dac157217.jpg"},{"id":64,"url":"https://telegra.ph/file/4a7163d0b9eff50e62c73.jpg"},{"id":65,"url":"https://telegra.ph/file/79f4141f6ab1d621cafcb.jpg"},{"id":66,"url":"https://telegra.ph/file/fd0bdb52a2d88e7a8fbdc.jpg"},{"id":67,"url":"https://telegra.ph/file/1ebf8b8a42786a195079f.jpg"},{"id":68,"url":"https://telegra.ph/file/ad325c4198e25e0b5999e.jpg"},{"id":69,"url":"https://telegra.ph/file/0a9ccc7a1231029d14279.jpg"},{"id":70,"url":"https://telegra.ph/file/53b8d2d8d6d86bea9a022.jpg"},{"id":71,"url":"https://telegra.ph/file/460f883b102d3cbb4b336.jpg"},{"id":72,"url":"https://telegra.ph/file/b25eb5ac549bc8fe6ddcf.jpg"},{"id":73,"url":"https://telegra.ph/file/6b4ee7432207dbe75c787.jpg"},{"id":74,"url":"https://telegra.ph/file/a6fa1d3245f95a463406e.jpg"},{"id":75,"url":"https://telegra.ph/file/36d40c65b1210c8ac9813.jpg"},{"id":76,"url":"https://telegra.ph/file/af2f47cc409fe33d25c03.jpg"},{"id":77,"url":"https://telegra.ph/file/165b579b4fc3305a8337e.jpg"},{"id":78,"url":"https://telegra.ph/file/b9a1f35c9d5c969a4839e.jpg"},{"id":79,"url":"https://telegra.ph/file/eb1a97aa4012ab5757642.jpg"},{"id":80,"url":"https://telegra.ph/file/df41fb00129fae7bd44bd.jpg"},{"id":81,"url":"https://telegra.ph/file/9133539e2606c003d8111.jpg"},{"id":82,"url":"https://telegra.ph/file/23c2e82f769bc11c8cd72.jpg"},{"id":83,"url":"https://telegra.ph/file/928c74902d467f31ffc2f.jpg"},{"id":84,"url":"https://telegra.ph/file/190fec8c34c650f024a77.jpg"},{"id":85,"url":"https://telegra.ph/file/eaf2a14ea07614447b5dc.jpg"},{"id":86,"url":"https://telegra.ph/file/349bf984fc4bec9c41bbb.jpg"},{"id":87,"url":"https://telegra.ph/file/550e3d97958510eb4de95.jpg"},{"id":88,"url":"https://telegra.ph/file/af5e92b50b1a4e24dfb15.jpg"},{"id":89,"url":"https://telegra.ph/file/63cf25f3e014d756561cc.jpg"},{"id":90,"url":"https://telegra.ph/file/dfe915a32ea65bc4f27e0.jpg"},{"id":91,"url":"https://telegra.ph/file/a5cb5827f004624f9b88b.jpg"},{"id":92,"url":"https://telegra.ph/file/f77744efeef8260a9115c.jpg"},{"id":93,"url":"https://telegra.ph/file/532f1051a1995c2a890de.jpg"},{"id":94,"url":"https://telegra.ph/file/a8d38f60cecd2d9bb775d.jpg"},{"id":95,"url":"https://telegra.ph/file/a78a7998daf13945c2399.jpg"},{"id":96,"url":"https://telegra.ph/file/7edb09cf4a89fc8858ccc.jpg"},{"id":97,"url":"https://telegra.ph/file/ce55ca7ed56039336d78f.jpg"},{"id":98,"url":"https://telegra.ph/file/8171765faea4943353225.jpg"},{"id":99,"url":"https://telegra.ph/file/48d68c0e015a08dc19686.jpg"},{"id":100,"url":"https://telegra.ph/file/3e02e1ecfee5bc79b48eb.jpg"},{"id":101,"url":"https://telegra.ph/file/23334ab832ee64f7bba0e.jpg"},{"id":102,"url":"https://telegra.ph/file/0b18af1ccd43f8d42b04f.jpg"},{"id":103,"url":"https://telegra.ph/file/14555c8f9dabe2d0e4261.jpg"},{"id":104,"url":"https://telegra.ph/file/d6f7543aacccc984990c7.jpg"},{"id":105,"url":"https://telegra.ph/file/d8282c880201d1492194a.jpg"},{"id":106,"url":"https://telegra.ph/file/d340cbc4ea5a208270b2e.jpg"},{"id":107,"url":"https://telegra.ph/file/eefe80b5b15ebaf4fded8.jpg"},{"id":108,"url":"https://telegra.ph/file/29364a06bb30d878d2417.jpg"},{"id":109,"url":"https://telegra.ph/file/e639c6349f1e046ff573c.jpg"},{"id":110,"url":"https://telegra.ph/file/4fe241cbaeebc4a77b480.jpg"},{"id":111,"url":"https://telegra.ph/file/1c26e01d0182b74ae0d5c.jpg"},{"id":112,"url":"https://telegra.ph/file/ccb05eb7c3f63a1693a93.jpg"},{"id":113,"url":"https://telegra.ph/file/5c84b7717b0f16c87df26.jpg"},{"id":114,"url":"https://telegra.ph/file/93a5049cd4a70a000c188.jpg"},{"id":115,"url":"https://telegra.ph/file/67af2191c11cf58ca8e5e.jpg"},{"id":116,"url":"https://telegra.ph/file/8fd573b9bff5be7383825.jpg"},{"id":117,"url":"https://telegra.ph/file/6e216a165573b706d932e.jpg"},{"id":118,"url":"https://telegra.ph/file/3c1a514a5f428e6eada99.jpg"},{"id":119,"url":"https://telegra.ph/file/23cd5622b85ad49629ff7.jpg"},{"id":120,"url":"https://telegra.ph/file/337ebee69e2c808269afa.jpg"},{"id":121,"url":"https://telegra.ph/file/cd6177c12621a2b2d8be3.jpg"},{"id":122,"url":"https://telegra.ph/file/5a5c2046411b0fe1e4b82.jpg"},{"id":123,"url":"https://telegra.ph/file/5bdb0ee2ada2335188a35.jpg"},{"id":124,"url":"https://telegra.ph/file/3203db1592c95ba896e20.jpg"}]}
