{"id":"0b9x-a1b4309f90","title":"柴系小乖稚乖画册--晴空-赤西夜夜-80D白丝-05-24","count":60,"cover":"https://telegra.ph/file/58e6b88325b0f842b0dea.jpg","photos":[{"id":1,"url":"https://telegra.ph/file/58e6b88325b0f842b0dea.jpg"},{"id":2,"url":"https://telegra.ph/file/1f534e98c64b7cb798e2e.jpg"},{"id":3,"url":"https://telegra.ph/file/f1991587d0156e7ba4540.jpg"},{"id":4,"url":"https://telegra.ph/file/8bacf520b3914deaaad37.jpg"},{"id":5,"url":"https://telegra.ph/file/6cc7c07bfd290db7e142b.jpg"},{"id":6,"url":"https://telegra.ph/file/5c3e2aa81d0e000d6c1b8.jpg"},{"id":7,"url":"https://telegra.ph/file/865c418d4da87aa93a6ed.jpg"},{"id":8,"url":"https://telegra.ph/file/964e8c686df52f324643e.jpg"},{"id":9,"url":"https://telegra.ph/file/6f1a6fe349419537cc87f.jpg"},{"id":10,"url":"https://telegra.ph/file/e2a17d75aae3a57ebfaf0.jpg"},{"id":11,"url":"https://telegra.ph/file/0874559515224e40d7eba.jpg"},{"id":12,"url":"https://telegra.ph/file/1d85f3e8a75906f66a409.jpg"},{"id":13,"url":"https://telegra.ph/file/14904bd063baf4d57f277.jpg"},{"id":14,"url":"https://telegra.ph/file/fa45d929e82dec529fe08.jpg"},{"id":15,"url":"https://telegra.ph/file/4366b11be7f1a248ea280.jpg"},{"id":16,"url":"https://telegra.ph/file/aecf0ca649a3f6d52a718.jpg"},{"id":17,"url":"https://telegra.ph/file/7e40abe5daf0e091088b5.jpg"},{"id":18,"url":"https://telegra.ph/file/32acaac9e5a4e15afd088.jpg"},{"id":19,"url":"https://telegra.ph/file/56b2c015d4e5d1d4abe7e.jpg"},{"id":20,"url":"https://telegra.ph/file/a73c5a8273d282bef8578.jpg"},{"id":21,"url":"https://telegra.ph/file/6479b0f87a762d214e482.jpg"},{"id":22,"url":"https://telegra.ph/file/0f4f92d440e48beee2cfa.jpg"},{"id":23,"url":"https://telegra.ph/file/46cc195b461eeb65324f0.jpg"},{"id":24,"url":"https://telegra.ph/file/6a9514d93a22fa11f9011.jpg"},{"id":25,"url":"https://telegra.ph/file/1975cde565b77cd762ada.jpg"},{"id":26,"url":"https://telegra.ph/file/efcd547b049280f44faca.jpg"},{"id":27,"url":"https://telegra.ph/file/a5496d21c2109f1e4deca.jpg"},{"id":28,"url":"https://telegra.ph/file/8424480da0508432f4d00.jpg"},{"id":29,"url":"https://telegra.ph/file/b3d07b4cf51c18c204cf8.jpg"},{"id":30,"url":"https://telegra.ph/file/734b992a85bf5e8597db4.jpg"},{"id":31,"url":"https://telegra.ph/file/a03b6ba69166ec2a9ce39.jpg"},{"id":32,"url":"https://telegra.ph/file/e3e78ea1bac948528e675.jpg"},{"id":33,"url":"https://telegra.ph/file/aaf27738f1db09b5a4b1d.jpg"},{"id":34,"url":"https://telegra.ph/file/fcaaf653b31213f559645.jpg"},{"id":35,"url":"https://telegra.ph/file/364b19097e16a1cb2f007.jpg"},{"id":36,"url":"https://telegra.ph/file/47fb4be8d98f0fb2df05d.jpg"},{"id":37,"url":"https://telegra.ph/file/cbfd73ec5263da4289068.jpg"},{"id":38,"url":"https://telegra.ph/file/6380a05b71770a46b5b34.jpg"},{"id":39,"url":"https://telegra.ph/file/eab76c4b11831ecdd8e66.jpg"},{"id":40,"url":"https://telegra.ph/file/da0356343d4b26e70583f.jpg"},{"id":41,"url":"https://telegra.ph/file/d95be24e2f15627b638bc.jpg"},{"id":42,"url":"https://telegra.ph/file/408becd139a9378d8e9fd.jpg"},{"id":43,"url":"https://telegra.ph/file/68af71ffae49cfdea3183.jpg"},{"id":44,"url":"https://telegra.ph/file/e544187922be1a6b4f53d.jpg"},{"id":45,"url":"https://telegra.ph/file/53a985c25b09620a70767.jpg"},{"id":46,"url":"https://telegra.ph/file/c90ffb6dfd14eb92c3793.jpg"},{"id":47,"url":"https://telegra.ph/file/ad49821f61e2921bece35.jpg"},{"id":48,"url":"https://telegra.ph/file/5828d73cd642a35252a92.jpg"},{"id":49,"url":"https://telegra.ph/file/ecf90a75673cbc0e2a179.jpg"},{"id":50,"url":"https://telegra.ph/file/0a8db3b25a148db60a305.jpg"},{"id":51,"url":"https://telegra.ph/file/c2093c3df175c825aec9d.jpg"},{"id":52,"url":"https://telegra.ph/file/2308ae7e8b883fb501550.jpg"},{"id":53,"url":"https://telegra.ph/file/065c8ca2053b0eeea7fa3.jpg"},{"id":54,"url":"https://telegra.ph/file/257bcdb43250c5debb524.jpg"},{"id":55,"url":"https://telegra.ph/file/4b28577af17f9042e509f.jpg"},{"id":56,"url":"https://telegra.ph/file/18a37b8000746e0070234.jpg"},{"id":57,"url":"https://telegra.ph/file/3971e458e6e045b79dde6.jpg"},{"id":58,"url":"https://telegra.ph/file/056d72806faa5ffeddd80.jpg"},{"id":59,"url":"https://telegra.ph/file/840b29441f39c26e86184.jpg"},{"id":60,"url":"https://telegra.ph/file/c68394e3a69abda0b0b72.jpg"}]}
